mkprobe/__init__.py
mkprobe/info.py
mkprobe/main.py
mkprobe-0.2.0.dist-info/licenses/LICENCE.md
mkprobe-0.2.0.dist-info/METADATA
mkprobe-0.2.0.dist-info/WHEEL
mkprobe-0.2.0.dist-info/entry_points.txt
mkprobe-0.2.0.dist-info/top_level.txt
mkprobe-0.2.0.dist-info/RECORD
