Metadata-Version: 2.4
Name: mkprobe
Version: 0.2.0
Summary: Rebuild contigs from serie of contiguous kmers formatted in fasta
Home-page: https://github.com/bio2m/mkprobe
Author: Benoit Guibert
Author-email: contact <contact@bio2m.fr>
License: GPLv3
Classifier: Development Status :: 4 - Beta
Classifier: Environment :: Console
Classifier: Intended Audience :: Science/Research
Classifier: License :: OSI Approved :: GNU General Public License v3 (GPLv3)
Classifier: Operating System :: POSIX :: Linux
Classifier: Programming Language :: Python :: 3
Classifier: Natural Language :: English
Classifier: Topic :: Scientific/Engineering :: Bio-Informatics
Requires-Python: >=3.8
License-File: LICENCE.md
Dynamic: author
Dynamic: author-email
Dynamic: classifier
Dynamic: description
Dynamic: description-content-type
Dynamic: home-page
Dynamic: license
Dynamic: license-file
Dynamic: requires-python
Dynamic: summary
